adminplus/__init__.py
adminplus/models.py
adminplus/sites.py
adminplus/tests.py
adminplus/templates/adminplus/base.html
adminplus/templates/adminplus/index.html
adminplus/templates/adminplus/test/index.html
django_adminplus-0.4.dist-info/DESCRIPTION.rst
django_adminplus-0.4.dist-info/METADATA
django_adminplus-0.4.dist-info/RECORD
django_adminplus-0.4.dist-info/WHEEL
django_adminplus-0.4.dist-info/metadata.json
django_adminplus-0.4.dist-info/pbr.json
django_adminplus-0.4.dist-info/top_level.txt
